drclient/__main__.py
drclient/extract.py
drclient/image.py
drclient/threaded_pull.py
drclient/version.py
drclient/cli/cmd_info.py
drclient/cli/cmd_pull.py
drclient/cli/main.py
drclient/registry/__init__.py
drclient/registry/manifest.py
drclient/registry/registry.py
drclient/registry/specs.py
drclient/view/console.py
drclient/view/history.py
drclient/view/info.py
tests/test_image_url.py
tests/test_pull.py
tests/test_version.py
drclient-0.0.7.dist-info/LICENSE
drclient-0.0.7.dist-info/METADATA
drclient-0.0.7.dist-info/WHEEL
drclient-0.0.7.dist-info/entry_points.txt
drclient-0.0.7.dist-info/top_level.txt
drclient-0.0.7.dist-info/RECORD
