Metadata-Version: 2.1
Name: drclient
Version: 0.0.7
Summary: A docker registry client command line utility and Python library
Home-page: https://github.com/joaompinto/drclient
Author: João Pinto
Author-email: lamego.pinto@gmail.com
License: MIT
License-File: LICENSE
Requires-Dist: requests
Requires-Dist: rich
Requires-Dist: typer
